{
  "mcpServers": {
    "chimera-vault": {
      "command": "D:\\MAS\\chimera-lite\\.venv\\Scripts\\python.exe",
      "args": ["D:\\MAS\\chimera-lite\\mcp-servers\\chimera-vault\\server.py"],
      "env": {
        "CHIMERA_VAULT_ROOT": "D:\\MAS\\project_chimera_vault"
      }
    },
    "chimera-papers": {
      "command": "D:\\MAS\\chimera-lite\\.venv\\Scripts\\python.exe",
      "args": ["D:\\MAS\\chimera-lite\\mcp-servers\\chimera-papers\\server.py"],
      "env": {
        "CHIMERA_PAPERS_ROOT": "D:\\MAS\\chimera-lite\\papers"
      }
    }
  }
}
